numcodecs_delta/__init__.py
numcodecs_delta/py.typed
numcodecs_delta-0.1.0.dist-info/METADATA
numcodecs_delta-0.1.0.dist-info/WHEEL
numcodecs_delta-0.1.0.dist-info/entry_points.txt
numcodecs_delta-0.1.0.dist-info/licenses/LICENSE
numcodecs_delta-0.1.0.dist-info/RECORD
