Metadata-Version: 2.4
Name: numcodecs-delta
Version: 0.1.0
Summary: Delta codecs for the `numcodecs` buffer compression API
License: Copyright (c) 2024, Juniper Tyree
License-File: LICENSE
Requires-Python: >=3.10
Requires-Dist: numcodecs<0.17,>=0.13.0
Requires-Dist: numpy~=2.0
Requires-Dist: typing-extensions~=4.6
